openwpm_utils/__init__.py
openwpm_utils/analysis.py
openwpm_utils/blocklist.py
openwpm_utils/database.py
openwpm_utils/domain.py
openwpm_utils/s3.py
openwpm_utils-0.2.0.dist-info/LICENSE
openwpm_utils-0.2.0.dist-info/METADATA
openwpm_utils-0.2.0.dist-info/WHEEL
openwpm_utils-0.2.0.dist-info/top_level.txt
openwpm_utils-0.2.0.dist-info/RECORD
