Metadata-Version: 2.1
Name: openwpm-utils
Version: 0.2.0
Summary: Tools for parsing crawl data generated by OpenWPM
Home-page: https://github.com/mozilla/openwpm-utils
Author: Steven Englehardt
Author-email: senglehardt@mozilla.com
License: MPL 2.0
Platform: UNKNOWN
Classifier: Development Status :: 3 - Alpha
Classifier: Environment :: Web Environment :: Mozilla
Classifier: Intended Audience :: Developers
Classifier: License :: OSI Approved :: Mozilla Public License 2.0 (MPL 2.0)
Classifier: Programming Language :: Python
Classifier: Programming Language :: Python :: 2
Classifier: Programming Language :: Python :: 2.7
Classifier: Programming Language :: Python :: 3
Classifier: Programming Language :: Python :: 3.5
Classifier: Programming Language :: Python :: 3.6
Classifier: Programming Language :: Python :: 3.7
Classifier: Topic :: Internet :: WWW/HTTP
Classifier: Topic :: Scientific/Engineering :: Information Analysis
Requires-Dist: boto3
Requires-Dist: ipaddress
Requires-Dist: jsbeautifier
Requires-Dist: pandas
Requires-Dist: plyvel
Requires-Dist: publicsuffix
Requires-Dist: pyarrow
Requires-Dist: pyspark
Requires-Dist: s3fs
Requires-Dist: six
